{
    "uuid": uuid,
    "date": date,
    "apk": {
        "type": "",
        "name": "",
        "s3_bucket": "",
        "s3_key": ""
    },
    "additional_files": [],
    "status": {
        "status": "",
        "notes": "",
        "start_time": "",
        "end_time": "",
    },
    "algorithm_status": {
        "storydistiller": {
            "status": "",
            "notes": "",
            "start_time": "",
            "end_time": "",
            "apk": ""
        },
        "owleye": {
            "status": "",
            "notes": "",
            "start_time": "",
            "end_time": "",
            "apk": ""
        },
        "xbot": {
            "status": "",
            "notes": "",
            "start_time": "",
            "end_time": "",
            "apk": ""
        },
        "gifdroid": {
            "status": "",
            "notes": "",
            "start_time": "",
            "end_time": "",
            "apk": ""
        },
        "ui_checker": {
            "status": "",
            "notes": "",
            "start_time": "",
            "end_time": "",
            "apk": ""
        }
    },
    "algorithm_outputs": {
        "storydistiller": "",
        "xbot": ""
    },
    "results": {
        "activities": [
            {
                "name": "",
                "image": [],
                "xbot": {
                    "image": "",
                    "description": ""
                },
                "owleye": {
                    "issues": []
                },
                "tapshoe": {
                    "image": [],
                    "description": "",
                    "heatmap": "{link to heatmap image}"
                }
            }
        ],
        "gifdroid": {
            "images": [],
            "json": []
        },
        "uichecker": {}
    }
}
